pyfladesk/__init__.py
PyFladesk-1.1.dist-info/LICENSE
PyFladesk-1.1.dist-info/METADATA
PyFladesk-1.1.dist-info/WHEEL
PyFladesk-1.1.dist-info/top_level.txt
PyFladesk-1.1.dist-info/RECORD
