Metadata-Version: 2.1
Name: PyFladesk
Version: 1.1
Summary: Create desktop application by using Flask and QtWebEngine
Home-page: https://github.com/smoqadam/PyFladesk
Author: ​Saeed Moqadam, Ezequiel Castaño​
Author-email: saeed.moqadam@gmail.com, castanoezequielleonardo@gmail.com
License: MIT
Requires-Dist: flask
Requires-Dist: pyqt5
Requires-Dist: pyqtwebengine
